gpsoauth/__init__.py
gpsoauth/google.py
gpsoauth/py.typed
gpsoauth/util.py
gpsoauth-1.0.4.dist-info/LICENSE
gpsoauth-1.0.4.dist-info/METADATA
gpsoauth-1.0.4.dist-info/WHEEL
gpsoauth-1.0.4.dist-info/RECORD
