Metadata-Version: 2.1
Name: gpsoauth
Version: 1.0.4
Summary: A python client library for Google Play Services OAuth.
Home-page: https://github.com/simon-weber/gpsoauth
License: MIT
Author: Simon Weber
Author-email: simon@simonmweber.com
Requires-Python: >=3.8,<4.0
Classifier: Development Status :: 5 - Production/Stable
Classifier: Intended Audience :: Developers
Classifier: License :: OSI Approved :: MIT License
Classifier: Operating System :: OS Independent
Classifier: Programming Language :: Python
Classifier: Programming Language :: Python :: 3
Classifier: Programming Language :: Python :: 3.8
Classifier: Programming Language :: Python :: 3.9
Classifier: Programming Language :: Python :: 3.10
Classifier: Programming Language :: Python :: 3.11
Classifier: Programming Language :: Python :: 3.12
Classifier: Typing :: Typed
Requires-Dist: pycryptodomex (>=3.0)
Requires-Dist: requests (>=2.0.0)
Requires-Dist: urllib3 (<2.0)
Project-URL: Repository, https://github.com/simon-weber/gpsoauth
